ml4co_kit/__init__.py
ml4co_kit/__pycache__/__init__.cpython-311.pyc
ml4co_kit/extension/gnn4co/__init__.py
ml4co_kit/extension/gnn4co/env/__init__.py
ml4co_kit/extension/gnn4co/env/denser.py
ml4co_kit/extension/gnn4co/env/env.py
ml4co_kit/extension/gnn4co/env/sparser.py
ml4co_kit/extension/gnn4co/env/dense/__init__.py
ml4co_kit/extension/gnn4co/env/dense/atsp.py
ml4co_kit/extension/gnn4co/env/dense/cvrp.py
ml4co_kit/extension/gnn4co/env/dense/tsp.py
ml4co_kit/extension/gnn4co/env/sparse/__init__.py
ml4co_kit/extension/gnn4co/env/sparse/atsp.py
ml4co_kit/extension/gnn4co/env/sparse/mcl.py
ml4co_kit/extension/gnn4co/env/sparse/mcut.py
ml4co_kit/extension/gnn4co/env/sparse/mis.py
ml4co_kit/extension/gnn4co/env/sparse/mvc.py
ml4co_kit/extension/gnn4co/env/sparse/tsp.py
ml4co_kit/extension/gnn4co/model/__init__.py
ml4co_kit/extension/gnn4co/model/model.py
ml4co_kit/extension/gnn4co/model/embedder/__init__.py
ml4co_kit/extension/gnn4co/model/embedder/atsp.py
ml4co_kit/extension/gnn4co/model/embedder/base.py
ml4co_kit/extension/gnn4co/model/embedder/cvrp.py
ml4co_kit/extension/gnn4co/model/embedder/mcl.py
ml4co_kit/extension/gnn4co/model/embedder/mcut.py
ml4co_kit/extension/gnn4co/model/embedder/mis.py
ml4co_kit/extension/gnn4co/model/embedder/mvc.py
ml4co_kit/extension/gnn4co/model/embedder/tsp.py
ml4co_kit/extension/gnn4co/model/embedder/utils.py
ml4co_kit/extension/gnn4co/model/encoder/__init__.py
ml4co_kit/extension/gnn4co/model/encoder/gnn_encoder.py
ml4co_kit/extension/gnn4co/model/encoder/gnn_encoder_tsp.py
ml4co_kit/extension/gnn4co/model/encoder/gnn_layer.py
ml4co_kit/extension/gnn4co/model/encoder/gnn_layer_tsp.py
ml4co_kit/extension/gnn4co/model/out_layer/__init__.py
ml4co_kit/extension/gnn4co/model/out_layer/base.py
ml4co_kit/extension/gnn4co/model/out_layer/edge.py
ml4co_kit/extension/gnn4co/model/out_layer/node.py
ml4co_kit/extension/gnn4co/model/out_layer/utils.py
ml4co_kit/extension/tsplib95/__init__.py
ml4co_kit/extension/tsplib95/bisep.py
ml4co_kit-0.4.2.dist-info/licenses/LICENSE
ml4co_kit-0.4.2.dist-info/METADATA
ml4co_kit-0.4.2.dist-info/WHEEL
ml4co_kit-0.4.2.dist-info/top_level.txt
ml4co_kit-0.4.2.dist-info/RECORD
