Metadata-Version: 2.4
Name: ml4co_kit
Version: 0.4.2
Summary: ml4co-kit provides convenient dataset generators for the combinatorial optimization problem
Home-page: https://github.com/Thinklab-SJTU/ML4CO-Kit
Author: SJTU-ReThinkLab
License: Mulan PSL v2
Classifier: License :: OSI Approved :: Mulan Permissive Software License v2 (MulanPSL-2.0)
Classifier: Programming Language :: Python
Classifier: Programming Language :: Python :: 3
Classifier: Programming Language :: Python :: 3.8
Classifier: Programming Language :: Python :: 3.9
Classifier: Programming Language :: Python :: 3.10
Classifier: Programming Language :: Python :: 3.11
Classifier: Programming Language :: Python :: 3.12
Classifier: Programming Language :: Python :: 3.13
Classifier: Programming Language :: Python :: 3 :: Only
Classifier: Programming Language :: Python :: Implementation :: CPython
Classifier: Operating System :: POSIX
Classifier: Operating System :: Unix
Classifier: Operating System :: MacOS
Classifier: Environment :: Console
Classifier: Topic :: Scientific/Engineering :: Artificial Intelligence
Classifier: Topic :: Scientific/Engineering :: Image Recognition
Classifier: Topic :: Scientific/Engineering :: Mathematics
Requires-Python: >=3.8
License-File: LICENSE
Requires-Dist: numpy>=1.24.3
Requires-Dist: networkx>=2.8.8
Requires-Dist: tqdm>=4.66.3
Requires-Dist: cython>=3.0.8
Requires-Dist: pulp>=2.8.0
Requires-Dist: scipy>=1.10.1
Requires-Dist: aiohttp>=3.10.11
Requires-Dist: requests>=2.32.0
Requires-Dist: matplotlib>=3.7.0
Requires-Dist: async_timeout>=4.0.3
Requires-Dist: pyvrp>=0.6.3
Requires-Dist: gurobipy>=11.0.3
Requires-Dist: scikit-learn>=1.3.0
Requires-Dist: ortools>=9.12.4544
Requires-Dist: huggingface_hub>=0.32.0
Requires-Dist: setuptools>=75.0.0
Requires-Dist: PySCIPOpt>=5.6.0
Dynamic: author
Dynamic: classifier
Dynamic: description
Dynamic: description-content-type
Dynamic: home-page
Dynamic: license
Dynamic: license-file
Dynamic: requires-dist
Dynamic: requires-python
Dynamic: summary
